{
    "id": "055ae6fc-7e18-4a39-8058-64082ca6d515",
    "encounter": {
        "code": null,
        "encounter_start": "2020-03-02",
        "description": "Ambulatory Encounter",
        "provider_id": "e2c226c2-3e1e-3d0b-b997-ce9544c10528",
        "facility_id": "5103c940-0c08-392f-95cd-446e0cea042a"
    },
    "symptoms": [
        {
            "description": [
                "cough",
                "sore throat",
                "severe fatigue",
                "muscle pain",
                "joint pain",
                "fever"
            ]
        }
    ],
    "demographics": {
        "name": "Jeffrey Greenfelder",
        "date_of_birth": "2005-01-16",
        "age": 15,
        "gender": "Male",
        "insurance": "Guardian"
    },
    "medications": [],
    "immunizations": [
        {
            "code": null,
            "description": "Influenza vaccine",
            "immunization_date": "2020-02-23"
        }
    ],
    "vitals": {
        "current": {
            "temperature": {
                "code": null,
                "value": 39.3,
                "unit": "°C"
            },
            "heart_rate": {
                "code": null,
                "value": 131.1,
                "unit": "/min"
            },
            "blood_pressure": {
                "systolic": {
                    "code": null,
                    "value": 120.0,
                    "unit": "mmHg"
                },
                "diastolic": {
                    "code": null,
                    "value": 73.0,
                    "unit": "mmHg"
                }
            },
            "respiratory_rate": {
                "code": null,
                "value": 27.6,
                "unit": "/min"
            },
            "oxygen_saturation": {
                "code": null,
                "value": 75.8,
                "unit": "%"
            },
            "weight": {
                "code": null,
                "value": 81.2,
                "unit": "kg"
            }
        },
        "baseline": {
            "vital_measurement_date": "2020-02-23",
            "height": {
                "code": null,
                "value": 155.0,
                "unit": "cm"
            },
            "weight": {
                "code": null,
                "value": 81.2,
                "unit": "kg"
            },
            "bmi": {
                "code": null,
                "value": 33.8,
                "unit": "kg/m²"
            },
            "bmi_percentile": {
                "code": null,
                "value": 99.1,
                "unit": "%"
            }
        }
    },
    "laboratory": {
        "covid19": {
            "code": "SARS-CoV-2",
            "description": "SARS-CoV-2 RNA test",
            "result": "Not detected"
        },
        "respiratory_panel": {
            "influenza_a": {
                "name": "Influenza A RNA",
                "result": "Negative"
            },
            "influenza_b": {
                "name": "Influenza B RNA",
                "result": "Negative"
            },
            "rsv": {
                "name": "RSV RNA",
                "result": "Negative"
            },
            "parainfluenza_1": {
                "name": "Parainfluenza virus 1 RNA",
                "result": "Negative"
            },
            "parainfluenza_2": {
                "name": "Parainfluenza virus 2 RNA",
                "result": "Negative"
            },
            "parainfluenza_3": {
                "name": "Parainfluenza virus 3 RNA",
                "result": "Negative"
            },
            "rhinovirus": {
                "name": "Rhinovirus RNA",
                "result": "Negative"
            },
            "metapneumovirus": {
                "name": "Human metapneumovirus RNA",
                "result": "Negative"
            },
            "adenovirus": {
                "name": "Adenovirus DNA",
                "result": "Negative"
            }
        }
    },
    "procedures": null,
    "care_plans": [
        {
            "description": "Face mask provided for immediate oxygen support",
            "start": null,
            "stop": null,
            "reasonCode": null,
            "reasonDescription": null
        },
        {
            "description": "Infectious disease care plan initiated",
            "start": "2020-03-02",
            "stop": null,
            "reasonCode": null,
            "reasonDescription": null
        },
        {
            "description": "Close monitoring required due to severe hypoxemia, tachycardia, age, and obesity risk factors",
            "start": null,
            "stop": null,
            "reasonCode": null,
            "reasonDescription": null
        },
        {
            "description": "Parent/patient education on home isolation protocols, warning signs, and return precautions",
            "start": null,
            "stop": null,
            "reasonCode": null,
            "reasonDescription": null
        },
        {
            "description": "Follow-up plan: Daily monitoring during acute phase, virtual check-ins as needed",
            "start": null,
            "stop": null,
            "reasonCode": null,
            "reasonDescription": null
        }
    ]
}